lookprime/__init__.py
lookprime/__main__.py
lookprime/api.py
lookprime/cli.py
lookprime/config.py
lookprime/core.py
lookprime/cpu.py
lookprime/mask.py
lookprime/sieve.py
lookprime-0.2.3.dist-info/licenses/LICENSE
lookprime-0.2.3.dist-info/METADATA
lookprime-0.2.3.dist-info/WHEEL
lookprime-0.2.3.dist-info/entry_points.txt
lookprime-0.2.3.dist-info/top_level.txt
lookprime-0.2.3.dist-info/RECORD
