Metadata-Version: 2.4
Name: lookprime
Version: 0.2.3
Summary: Ultra-fast prime lookup using memory-mapped odd-only sieve
Author: Your Name
License: MIT
Requires-Python: >=3.9
License-File: LICENSE
Dynamic: license-file
